imysql/__init__.py
imysql/imc.py
imysql-1.1.0.dist-info/METADATA
imysql-1.1.0.dist-info/WHEEL
imysql-1.1.0.dist-info/top_level.txt
imysql-1.1.0.dist-info/RECORD
